cdot_tree_sitter_python-0.21.0-cp38-abi3-macosx_10_9_x86_64.whl
cdot_tree_sitter_python-0.21.0-cp38-abi3-macosx_13_0_arm64.whl
cdot_tree_sitter_python-0.21.0-cp38-abi3-manylinux1_i686.manylinux2014_i686.manylinux_2_17_i686.manylinux_2_5_i686.whl
cdot_tree_sitter_python-0.21.0-cp38-abi3-manylinux1_x86_64.manylinux2014_x86_64.manylinux_2_17_x86_64.manylinux_2_5_x86_64.whl
cdot_tree_sitter_python-0.21.0-cp38-abi3-musllinux_1_1_i686.whl
cdot_tree_sitter_python-0.21.0-cp38-abi3-musllinux_1_1_x86_64.whl
cdot_tree_sitter_python/__init__.py
cdot_tree_sitter_python/__init__.pyi
cdot_tree_sitter_python/_binding.abi3.so
cdot_tree_sitter_python/binding.c
cdot_tree_sitter_python/py.typed
cdot_tree_sitter_python/queries/highlights.scm
cdot_tree_sitter_python/queries/tags.scm
cdot_tree_sitter_python-0.21.0.dist-info/LICENSE
cdot_tree_sitter_python-0.21.0.dist-info/METADATA
cdot_tree_sitter_python-0.21.0.dist-info/WHEEL
cdot_tree_sitter_python-0.21.0.dist-info/top_level.txt
cdot_tree_sitter_python-0.21.0.dist-info/RECORD
