Metadata-Version: 2.1
Name: cdot_tree-sitter-python
Version: 0.21.0
Summary: Python grammar for tree-sitter
Author: Max Brunsfeld, Amaan Qureshi
License: MIT
Keywords: parsing,incremental,python
Classifier: Development Status :: 4 - Beta
Classifier: Intended Audience :: Developers
Classifier: License :: OSI Approved :: MIT License
Classifier: Topic :: Software Development :: Compilers
Classifier: Topic :: Text Processing :: Linguistic
Requires-Python: >=3.8
License-File: LICENSE
Provides-Extra: core
Requires-Dist: tree-sitter ~=0.21 ; extra == 'core'
